tests/__init__.py
tests/test_thinkcell.py
thinkcell/__init__.py
thinkcell/thinkcell.py
thinkcell-21.10.12.dist-info/LICENSE
thinkcell-21.10.12.dist-info/METADATA
thinkcell-21.10.12.dist-info/WHEEL
thinkcell-21.10.12.dist-info/top_level.txt
thinkcell-21.10.12.dist-info/RECORD
