Metadata-Version: 2.1
Name: thinkcell
Version: 21.10.12
Summary: Small utility to automate the generation of think-cell graphs.
Home-page: https://github.com/duarteocarmo/think-cell
Author: Duarte O.Carmo
Author-email: duarteocarmo@gmail.com
License: MIT
Project-URL: Bug Reports, https://github.com/duarteocarmo/think-cell/issues
Project-URL: Say Thanks!, https://duarteocarmo.com
Project-URL: Source, https://github.com/duarteocarmo/think-cell
Keywords: automation powerpoint thinkcell ppttc business consulting
Platform: UNKNOWN
Classifier: Programming Language :: Python :: 3.6
Classifier: Programming Language :: Python :: 3.7
Classifier: Programming Language :: Python :: 3.8
Classifier: Programming Language :: Python :: 3.9
Classifier: License :: OSI Approved :: MIT License
Classifier: Operating System :: OS Independent
Requires-Python: >=3.6
License-File: LICENSE
